{"nodes":[{"id":0,"name":"Provinsi Jawa Tengah","group":1},{"id":1,"name":"Provinsi Jawa Tengah","group":2},{"id":2,"name":"Kota Semarang","group":2},{"id":3,"name":"Kementerian Kelautan Dan Perikanan","group":2},{"id":4,"name":"Kementerian Perhubungan","group":2},{"id":5,"name":"Kementerian Kesehatan","group":2},{"id":6,"name":"Kabupaten Klaten","group":2},{"id":7,"name":"Badan Diklat dan Pelatihan Prov. Jateng","jumlahlelangsatker":64,"group":3},{"id":8,"name":"RSUD Prof. Dr. Margono Soekarjo Purwoketo","jumlahlelangsatker":127,"group":3},{"id":9,"name":"RSJD Surakarta","jumlahlelangsatker":40,"group":3},{"id":10,"name":"Dinas Energi dan Sumber Daya Mineral","jumlahlelangsatker":173,"group":3},{"id":11,"name":"Dinas Perhubungan Komunikasi dan Informatika Provinsi Jawa Tengah","jumlahlelangsatker":127,"group":3},{"id":12,"name":"Dinas Pendidikan Provinsi Jawa Tengah","jumlahlelangsatker":61,"group":3},{"id":13,"name":"RSUD Dr. Moewardi Surakarta","jumlahlelangsatker":47,"group":3},{"id":14,"name":"Badan Arsip Dan Perpustakaan","jumlahlelangsatker":42,"group":3},{"id":15,"name":"Dinas Pengelolaan Sumber Daya Air","jumlahlelangsatker":335,"group":3},{"id":16,"name":"Dinas Perkebunan Prov. Jateng","jumlahlelangsatker":235,"group":3},{"id":17,"name":"Dinas Tenaga Kerja Transmigrasi dan Kependudukan","jumlahlelangsatker":88,"group":3},{"id":18,"name":"Panitia Pengadaan Konstruksi DINAKKESWAN APBD","jumlahlelangsatker":33,"group":3},{"id":19,"name":"Dinas Kelautan dan Perikanan","jumlahlelangsatker":107,"group":3},{"id":20,"name":"Dinas Pertanian Tanaman Pangan dan Hortikultura","jumlahlelangsatker":192,"group":3},{"id":21,"name":"Balai Pelaksana Teknis Bina Marga Wilayah Purwodadi","jumlahlelangsatker":50,"group":3},{"id":22,"name":"DINAS BINA MARGAPROVINSI JAWA TENGAH","jumlahlelangsatker":26,"group":3},{"id":23,"name":"BALAI PELAKSANA TEKNIS BINA MARGA WILAYAH PEKALONGAN","jumlahlelangsatker":35,"group":3},{"id":24,"name":"Dinas Bina Marga Prov. Jateng","jumlahlelangsatker":1069,"group":3},{"id":25,"name":"BPT BINA MARGA WILAYAH SURAKARTA","jumlahlelangsatker":28,"group":3},{"id":26,"name":"BPT BINA MARGA WILAYAH MAGELANG","jumlahlelangsatker":50,"group":3},{"id":27,"name":"BPT BINA MARGA WILAYAH TEGAL","jumlahlelangsatker":42,"group":3},{"id":28,"name":"BPT BINA MARGA WILAYAH SEMARANG","jumlahlelangsatker":22,"group":3},{"id":29,"name":"Panitia Pengadaan Barang\/Jasa DINAKKESWAN APBD","jumlahlelangsatker":63,"group":3},{"id":30,"name":"Dinas Cipta Karya Dan Tata Ruang Provinsi Jawa Tengah","jumlahlelangsatker":242,"group":3},{"id":31,"name":"Dinas Kesehatan Prov. Jateng","jumlahlelangsatker":187,"group":3},{"id":32,"name":"RSUP Dr. Soeradji Tirtonegoro","jumlahlelangsatker":80,"group":3},{"id":33,"name":"Dinas Kelautan dan Perikanan Provinsi Jawa Tengah","jumlahlelangsatker":83,"group":3},{"id":34,"name":"Satuan Kerja Pengembangan LLASDP Jawa Tengah","jumlahlelangsatker":35,"group":3},{"id":35,"name":"Panitia Pengadaan Barang\/Jasa DINAKKESWAN APBN","jumlahlelangsatker":49,"group":3},{"id":36,"name":"Panitia Pengadaan Konstruksi DINAKKESWAN APBN","jumlahlelangsatker":128,"group":3},{"id":37,"name":"Dinas Kependudukan Dan Pencatatan Sipil","jumlahlelangsatker":12,"group":3},{"id":38,"name":"Badan Pendidikan dan Pelatihan","jumlahlelangsatker":65,"group":3},{"id":39,"name":"Dinas Perhubungan Komunikasi dan Informatika","jumlahlelangsatker":146,"group":3},{"id":40,"name":"Dinas Kesehatan","jumlahlelangsatker":120,"group":3},{"id":41,"name":"Dinas Bina Marga","jumlahlelangsatker":39,"group":3},{"id":42,"name":"BPT BINA MARGA WILAYAH PURWODADI","jumlahlelangsatker":25,"group":3},{"id":43,"name":"BPT BINA MARGA WILAYAH CILACAP","jumlahlelangsatker":14,"group":3},{"id":44,"name":"BPT BINA MARGA WILAYAH PEKALONGAN","jumlahlelangsatker":29,"group":3},{"id":45,"name":"BADAN PENDIDIKAN DAN PELATIHAN PROV. JATENG","jumlahlelangsatker":30,"group":3},{"id":46,"name":"DINAS BINAMARGA PROV. JATENG","jumlahlelangsatker":351,"group":3},{"id":47,"name":"DINAS ESDM PROV. JATENG","jumlahlelangsatker":26,"group":3},{"id":48,"name":"Dinas Pendapatan dan Pengelolaan Aset Daerah Prov. Jateng","jumlahlelangsatker":100,"group":3},{"id":49,"name":"Dinas Kelautan dan Perikanan Provinsi Jawa Tengah (07)","jumlahlelangsatker":51,"group":3},{"id":50,"name":"Satuan Kerja Perhubungan Darat Provinsi Jawa Tengah","jumlahlelangsatker":54,"group":3},{"id":51,"name":"Agency Rumah Sakit Paru Dr. H. A. Rotinsulu","jumlahlelangsatker":64,"group":3},{"id":52,"name":"RSUP. Dr. Hasan Sadikin Bandung","jumlahlelangsatker":182,"group":3},{"id":53,"name":"RSUP dr. SOERADJI TIRTONEGORO","jumlahlelangsatker":80,"group":3},{"id":54,"name":"Rumah Sakit Mata Cicendo","jumlahlelangsatker":91,"group":3},{"id":55,"name":"Dinas Kesehatan","jumlahlelangsatker":120,"group":3},{"id":56,"name":"PT. PESONA PERMATA BUANA","jumlahmenang":18,"lelangmenang":"21042, 191042, 935042, 2114042, 2123042, 2928042, 3034042, 3604042, 3656042, 4191042, 4230042, 4410042, 4477042, 4510042, 5191042, 5534042, 5573042, 9488042","menangperpenawaran":0.818182,"group":4},{"id":57,"name":"CV Mutiara Hati","jumlahmenang":6,"lelangmenang":"2118042, 2236042, 2597042, 4686042, 5379042, 5616042","menangperpenawaran":1,"group":4},{"id":58,"name":"PT. ARSA SAMUDRA MAS","jumlahmenang":5,"lelangmenang":"133042, 1425042, 2493042, 3232042, 3723042","menangperpenawaran":0.833333,"group":5},{"id":59,"name":"CV. PRIMA 137","jumlahmenang":13,"lelangmenang":"198042, 1215042, 1419042, 1501042, 1503042, 1606042, 1629042, 1811042, 3062042, 3072042, 3287042, 3440042, 3714042","menangperpenawaran":0.684211,"group":4},{"id":60,"name":"CV. SOLUSI ARYA PRIMA","jumlahmenang":7,"lelangmenang":"199042, 305042, 1611042, 4867042, 6458042, 9944042, 9990042","menangperpenawaran":0.7,"group":5},{"id":61,"name":"cv. BISMA KARYA MEDIKA","jumlahmenang":7,"lelangmenang":"73042, 238042, 1551042, 2272042, 4192042, 5471042, 6901042","menangperpenawaran":0.5,"group":4},{"id":62,"name":"CV. Studi Teknik","jumlahmenang":5,"lelangmenang":"3021042, 4610042, 4658042, 6257042, 6334042","menangperpenawaran":0.294118,"group":4},{"id":63,"name":"CV. Madani Callysta Saibuyun","jumlahmenang":13,"lelangmenang":"2805042, 3256042, 4573042, 6483042, 6614042, 6821042, 8054042, 8457042, 8490042, 8556042, 9007042, 9120042, 9400042","menangperpenawaran":0.481481,"group":4},{"id":64,"name":"PT. PROPORSI","jumlahmenang":5,"lelangmenang":"2900042, 4548042, 4821042, 5082042, 6605042","menangperpenawaran":0.5,"group":4},{"id":65,"name":"PT. Trikarsa Buwana Persada Gemilang","jumlahmenang":10,"lelangmenang":"2853042, 4438042, 5331042, 6460042, 6666042, 6689042, 8542042, 8682042, 8742042, 9573042","menangperpenawaran":0.5,"group":4},{"id":66,"name":"PT. INDOTAMA MAHESA KARYA","jumlahmenang":7,"lelangmenang":"3023042, 3024042, 4558042, 5412042, 6326042, 7036042, 8975042","menangperpenawaran":0.538462,"group":4},{"id":67,"name":"CV. MEKAR CEMERLANG ABADI","jumlahmenang":5,"lelangmenang":"3578042, 7033042, 7175042, 7184042, 9393042","menangperpenawaran":0.555556,"group":4},{"id":68,"name":"CV. JAVA DESIGN CONSULTANT","jumlahmenang":11,"lelangmenang":"5346042, 5399042, 5548042, 6526042, 6732042, 8234042, 8335042, 8451042, 8978042, 9672042, 9809042","menangperpenawaran":0.6875,"group":4},{"id":69,"name":"CV. KARINA BUANA ABADI","jumlahmenang":7,"lelangmenang":"101042, 1010042, 1080042, 1081042, 2482042, 2508042, 2513042","menangperpenawaran":1,"group":4},{"id":70,"name":"PT. EZRA PRATAMA","jumlahmenang":5,"lelangmenang":"843042, 951042, 1130042, 2112042, 9661042","menangperpenawaran":0.833333,"group":4},{"id":71,"name":"JURUS TRAFFINDO","jumlahmenang":8,"lelangmenang":"1039042, 1040042, 2273042, 2330042, 2337042, 2484042, 2515042, 3549042","menangperpenawaran":0.615385,"group":4},{"id":72,"name":"PRAMULYATAMA","jumlahmenang":5,"lelangmenang":"1011042, 1042042, 2509042, 4717042, 4718042","menangperpenawaran":0.625,"group":4},{"id":73,"name":"PT. TUMBUH JAYA DESAIN","jumlahmenang":5,"lelangmenang":"1539042, 2428042, 2528042, 3233042, 5195042","menangperpenawaran":1,"group":4},{"id":74,"name":"PT. TELEKOMUNIKASI INDONESIA TBK","jumlahmenang":5,"lelangmenang":"2111042, 2495042, 3718042, 5776042, 7559042","menangperpenawaran":1,"group":5},{"id":75,"name":"CV. SOLUSI ARYA PRIMA","jumlahmenang":7,"lelangmenang":"1246042, 1576042, 1602042, 3537042, 3608042, 5619042, 5620042","menangperpenawaran":0.583333,"group":4},{"id":76,"name":"PT.TRI DELTA JAYA","jumlahmenang":9,"lelangmenang":"92042, 214042, 1675042, 4629042, 7046042, 7364042, 7399042, 9948042, 10096042","menangperpenawaran":0.692308,"group":5},{"id":77,"name":"CV. DUTA NUSINDO","jumlahmenang":8,"lelangmenang":"108042, 1066042, 2988042, 3533042, 5245042, 7026042, 9808042, 9940042","menangperpenawaran":0.571429,"group":4},{"id":78,"name":"CV. SOLUSI ARYA PRIMA","jumlahmenang":6,"lelangmenang":"225042, 234042, 241042, 1620042, 1758042, 1791042","menangperpenawaran":1,"group":4},{"id":79,"name":"CV. SUMBER MAS","jumlahmenang":5,"lelangmenang":"1458042, 2423042, 4896042, 6465042, 7351042","menangperpenawaran":0.555556,"group":4},{"id":80,"name":"MEGAH KARYA TIKA PRATAMA","jumlahmenang":5,"lelangmenang":"1376042, 2294042, 3038042, 3308042, 4889042","menangperpenawaran":0.5,"group":4},{"id":81,"name":"PT.CIPTA EKAPURNA ENGINEERING CONSULTANT","jumlahmenang":7,"lelangmenang":"2559042, 2561042, 4151042, 6109042, 8537042, 8575042, 9238042","menangperpenawaran":0.538462,"group":4},{"id":82,"name":"PT. PRIMADANI","jumlahmenang":8,"lelangmenang":"2289042, 2290042, 4453042, 4454042, 6276042, 7271042, 8197042, 8198042","menangperpenawaran":0.8,"group":4},{"id":83,"name":"PT. ANNABA PERSADA","jumlahmenang":6,"lelangmenang":"2366042, 2639042, 4162042, 6545042, 8272042, 9413042","menangperpenawaran":0.545455,"group":4},{"id":84,"name":"CV. TEKTURA PANCAMITRA","jumlahmenang":7,"lelangmenang":"2370042, 2638042, 6158042, 7281042, 8271042, 8534042, 8572042","menangperpenawaran":0.5,"group":4},{"id":85,"name":"CV. MUTIARA","jumlahmenang":5,"lelangmenang":"2421042, 4894042, 6271042, 6468042, 8202042","menangperpenawaran":1,"group":4},{"id":86,"name":"CV. TRIDAYA ENGINEERING CONSULTANT","jumlahmenang":5,"lelangmenang":"2468042, 2469042, 4164042, 6156042, 8401042","menangperpenawaran":0.625,"group":4},{"id":87,"name":"CV.MEKAR","jumlahmenang":5,"lelangmenang":"2557042, 4152042, 6110042, 6546042, 8818042","menangperpenawaran":0.454545,"group":4},{"id":88,"name":"cv.malta perkasa","jumlahmenang":5,"lelangmenang":"3293042, 3294042, 4774042, 6466042, 8497042","menangperpenawaran":0.833333,"group":4},{"id":89,"name":"BARUNA MITRATAMA","jumlahmenang":6,"lelangmenang":"1014042, 1497042, 3111042, 3112042, 3413042, 4582042","menangperpenawaran":0.857143,"group":4},{"id":90,"name":"CV. Andaya Prima","jumlahmenang":7,"lelangmenang":"1085042, 1263042, 1360042, 1362042, 2388042, 2564042, 3407042","menangperpenawaran":0.318182,"group":4},{"id":91,"name":"CV. SETYA UTAMA","jumlahmenang":8,"lelangmenang":"2189042, 2305042, 3410042, 4089042, 4092042, 4918042, 5559042, 5618042","menangperpenawaran":0.333333,"group":4},{"id":92,"name":"BAGASTAMA","jumlahmenang":8,"lelangmenang":"1494042, 3114042, 3115042, 4387042, 4707042, 4807042, 5299042, 6709042","menangperpenawaran":0.571429,"group":4},{"id":93,"name":"SHIMA ABIMANTRANA","jumlahmenang":8,"lelangmenang":"1013042, 1359042, 2186042, 4087042, 4102042, 5453042, 5470042, 7927042","menangperpenawaran":0.285714,"group":4},{"id":94,"name":"CV. UTAMI","jumlahmenang":5,"lelangmenang":"1226042, 3116042, 4581042, 7333042, 7349042","menangperpenawaran":0.714286,"group":4},{"id":95,"name":"CV VALNEZ","jumlahmenang":6,"lelangmenang":"2875042, 3412042, 4100042, 4101042, 4103042, 5381042","menangperpenawaran":0.375,"group":4},{"id":96,"name":"RAMA UTAMA","jumlahmenang":6,"lelangmenang":"1496042, 3110042, 4580042, 5467042, 5495042, 5528042","menangperpenawaran":0.375,"group":4},{"id":97,"name":"CV. BALAWA MITRATAMA","jumlahmenang":5,"lelangmenang":"3118042, 3539042, 4916042, 4963042, 4965042","menangperpenawaran":0.416667,"group":4},{"id":98,"name":"PT. KALISARI RAYA ABADI","jumlahmenang":6,"lelangmenang":"967042, 968042, 970042, 3259042, 3261042, 4705042","menangperpenawaran":0.375,"group":4},{"id":99,"name":"CV. SETYA UTAMA","jumlahmenang":5,"lelangmenang":"2089042, 4467042, 4609042, 4613042, 4614042","menangperpenawaran":0.555556,"group":4},{"id":100,"name":"CV. KARYA HANDAYANI","jumlahmenang":6,"lelangmenang":"863013, 1308013, 1548013, 1549013, 1555013, 2453013","menangperpenawaran":1,"group":4},{"id":101,"name":"CV. SURYA BUANA","jumlahmenang":5,"lelangmenang":"1389042, 1504042, 1508042, 4762042, 10019042","menangperpenawaran":0.294118,"group":4},{"id":102,"name":"CV. PUTRA UTAMA PERKASA","jumlahmenang":5,"lelangmenang":"1186042, 1687042, 1688042, 2601042, 5095042","menangperpenawaran":0.555556,"group":4},{"id":103,"name":"CV. Bintang Permana","jumlahmenang":6,"lelangmenang":"1388042, 1422042, 3477042, 5436042, 7488042, 8104042","menangperpenawaran":0.428571,"group":4},{"id":104,"name":"CV.Melati Sari Abadi","jumlahmenang":16,"lelangmenang":"1725042, 2244042, 3270042, 3475042, 3575042, 4765042, 4850042, 6508042, 6617042, 6630042, 6878042, 7267042, 7546042, 8219042, 8300042, 8505042","menangperpenawaran":0.64,"group":5},{"id":105,"name":"CV. BANGUN INDAH","jumlahmenang":5,"lelangmenang":"1524042, 3192042, 3194042, 5009042, 5157042","menangperpenawaran":0.555556,"group":4},{"id":106,"name":"CV. BUNGA KENCANA","jumlahmenang":6,"lelangmenang":"1685042, 2243042, 4763042, 5437042, 7417042, 8122042","menangperpenawaran":1,"group":4},{"id":107,"name":"CV.OCTAVIANA","jumlahmenang":9,"lelangmenang":"3055042, 5672042, 6888042, 7339042, 7473042, 9142042, 9893042, 9896042, 10112042","menangperpenawaran":0.5625,"group":4},{"id":108,"name":"CV. BAROKAH ABADI","jumlahmenang":7,"lelangmenang":"352042, 1935042, 1936042, 2137042, 2138042, 2139042, 2140042","menangperpenawaran":0.777778,"group":4},{"id":109,"name":"KURNIA PATRIA","jumlahmenang":5,"lelangmenang":"1934042, 1937042, 1938042, 1939042, 1945042","menangperpenawaran":0.555556,"group":4},{"id":110,"name":"CV.HEKSA MANDIRI","jumlahmenang":5,"lelangmenang":"1565042, 2037042, 2040042, 2042042, 2056042","menangperpenawaran":0.833333,"group":4},{"id":111,"name":"BINTANG MULYA","jumlahmenang":5,"lelangmenang":"516042, 2007042, 2008042, 2009042, 2085042","menangperpenawaran":0.833333,"group":4},{"id":112,"name":"CV. DULCHOMINDO","jumlahmenang":5,"lelangmenang":"383042, 390042, 392042, 1895042, 1899042","menangperpenawaran":0.277778,"group":4},{"id":113,"name":"PT. JAYA SEMPURNA SAKTI","jumlahmenang":17,"lelangmenang":"1845042, 1848042, 3916042, 5822042, 5830042, 5836042, 7089042, 7095042, 7096042, 7111042, 7605042, 7621042, 7628042, 7629042, 7688042, 7689042, 8261042","menangperpenawaran":0.361702,"group":4},{"id":114,"name":"PT. PADAT SARI PERKASA","jumlahmenang":5,"lelangmenang":"1830042, 1852042, 1860042, 3759042, 4266042","menangperpenawaran":0.555556,"group":4},{"id":115,"name":"PT. ARMADA HADA GRAHA","jumlahmenang":18,"lelangmenang":"1874042, 2172042, 2173042, 3787042, 3797042, 4281042, 4285042, 5595042, 5844042, 5868042, 5870042, 7078042, 7083042, 7630042, 7633042, 7648042, 8040042, 9865042","menangperpenawaran":0.580645,"group":5},{"id":116,"name":"PT.MARGA KARYA","jumlahmenang":15,"lelangmenang":"1861042, 3757042, 3767042, 3781042, 3782042, 3813042, 3845042, 4489042, 5802042, 5826042, 5869042, 6190042, 7590042, 7659042, 7789042","menangperpenawaran":0.483871,"group":5},{"id":117,"name":"Pt. Deltamarga Adyatama","jumlahmenang":14,"lelangmenang":"1833042, 1834042, 1884042, 4503042, 4738042, 4739042, 5795042, 5845042, 7062042, 7122042, 7595042, 7598042, 7663042, 7672042","menangperpenawaran":0.5,"group":5},{"id":118,"name":"PT. UNGGUL PERDANA MULYA","jumlahmenang":5,"lelangmenang":"1887042, 4292042, 5811042, 5825042, 5862042","menangperpenawaran":0.2,"group":4},{"id":119,"name":"PT DUTA MAS INDAH","jumlahmenang":10,"lelangmenang":"1835042, 1872042, 3761042, 5820042, 7615042, 7616042, 7623042, 7662042, 7664042, 7679042","menangperpenawaran":0.47619,"group":5},{"id":120,"name":"PT. PONCOREDJO","jumlahmenang":11,"lelangmenang":"1839042, 4297042, 4500042, 5804042, 5808042, 6171042, 7109042, 7235042, 7657042, 8263042, 8265042","menangperpenawaran":0.354839,"group":5},{"id":121,"name":"PRIMA DUTA KENCANA","jumlahmenang":6,"lelangmenang":"5838042, 5853042, 5858042, 7592042, 7594042, 7612042","menangperpenawaran":0.428571,"group":5},{"id":122,"name":"PT. PANEN ISHI CONS","jumlahmenang":7,"lelangmenang":"3738042, 3801042, 3804042, 5593042, 5865042, 7090042, 7430042","menangperpenawaran":0.411765,"group":4},{"id":123,"name":"PT. Satya Cipta Perkasa","jumlahmenang":8,"lelangmenang":"1850042, 5591042, 5859042, 5861042, 6025042, 7610042, 7626042, 7994042","menangperpenawaran":0.5,"group":4},{"id":124,"name":"PT. SEMARANG MULTI CONS","jumlahmenang":16,"lelangmenang":"1856042, 3741042, 3777042, 3792042, 3807042, 5854042, 5860042, 5863042, 5864042, 5875042, 7588042, 7596042, 7604042, 7606042, 7608042, 7642042","menangperpenawaran":0.615385,"group":5},{"id":125,"name":"pt nurcahya jaya mandiri","jumlahmenang":11,"lelangmenang":"1857042, 3812042, 5827042, 5832042, 7093042, 7094042, 7186042, 7591042, 7609042, 7685042, 9868042","menangperpenawaran":0.5,"group":4},{"id":126,"name":"PT. MOHANDAS OELOENG","jumlahmenang":14,"lelangmenang":"2169042, 3786042, 3788042, 3811042, 5596042, 5823042, 5878042, 5913042, 5918042, 7593042, 7678042, 7816042, 7822042, 7829042","menangperpenawaran":0.56,"group":4},{"id":127,"name":"PT. ARTHA BINA SEDAYA","jumlahmenang":9,"lelangmenang":"1863042, 1885042, 3734042, 3775042, 5793042, 5803042, 7077042, 7238042, 7658042","menangperpenawaran":0.36,"group":4},{"id":128,"name":"PT. ANEKA BANGUN SARANA","jumlahmenang":6,"lelangmenang":"1865042, 1883042, 5850042, 6165042, 6167042, 7075042","menangperpenawaran":0.666667,"group":5},{"id":129,"name":"PT. KARYA ADI KENCANA","jumlahmenang":10,"lelangmenang":"1866042, 1867042, 1871042, 3803042, 5594042, 5828042, 5871042, 7081042, 7617042, 7681042","menangperpenawaran":0.666667,"group":5},{"id":130,"name":"PT. TERUS JAYA SANTOSA","jumlahmenang":5,"lelangmenang":"1879042, 4742042, 4743042, 5816042, 5876042","menangperpenawaran":0.625,"group":4},{"id":131,"name":"PT. CAHAYA SEMPURNA SEJATI","jumlahmenang":5,"lelangmenang":"1881042, 1886042, 7072042, 7654042, 7669042","menangperpenawaran":0.625,"group":5},{"id":132,"name":"PT.TIRTA YASA","jumlahmenang":5,"lelangmenang":"2167042, 7070042, 7656042, 7660042, 7661042","menangperpenawaran":0.5,"group":4},{"id":133,"name":"CV.SERAYU SAKTI","jumlahmenang":18,"lelangmenang":"2084042, 2098042, 2100042, 2102042, 2103042, 2104042, 2105042, 2107042, 2108042, 6127042, 6128042, 6129042, 6131042, 6132042, 6135042, 6136042, 6140042, 6141042","menangperpenawaran":1,"group":4},{"id":134,"name":"PT. MUARA PERDANA","jumlahmenang":8,"lelangmenang":"2150042, 4444042, 4449042, 6137042, 6138042, 6139042, 7469042, 7915042","menangperpenawaran":1,"group":5},{"id":135,"name":"PT.CITRANUSA GRAHA PERSADAJAYA","jumlahmenang":7,"lelangmenang":"2164042, 5599042, 5661042, 5799042, 5807042, 5813042, 6163042","menangperpenawaran":0.875,"group":5},{"id":136,"name":"PT. NEW CAKTI","jumlahmenang":5,"lelangmenang":"2168042, 5846042, 5867042, 7622042, 7644042","menangperpenawaran":1,"group":5},{"id":137,"name":"PT. SEMPALAN TEKNOLOGI NASIONAL","jumlahmenang":8,"lelangmenang":"2170042, 3748042, 3798042, 3802042, 4269042, 4271042, 4295042, 7675042","menangperpenawaran":0.533333,"group":5},{"id":138,"name":"CV. SUNDUS KARYA PERDANA","jumlahmenang":7,"lelangmenang":"4416042, 5887042, 5964042, 5983042, 6319042, 6389042, 7945042","menangperpenawaran":0.304348,"group":4},{"id":139,"name":"PT CITRA CIPTAADIGUNA","jumlahmenang":8,"lelangmenang":"4478042, 5792042, 5800042, 5833042, 5839042, 5841042, 7676042, 7677042","menangperpenawaran":0.470588,"group":5},{"id":140,"name":"PT.KARYA BISA","jumlahmenang":7,"lelangmenang":"4283042, 4296042, 4298042, 5589042, 5590042, 7680042, 7687042","menangperpenawaran":0.4375,"group":4},{"id":141,"name":"PT. KARTIKA JATI SENTOSA","jumlahmenang":5,"lelangmenang":"3755042, 4488042, 5824042, 5851042, 7790042","menangperpenawaran":0.5,"group":4},{"id":142,"name":"PT. SINAR UTAMA KARYA","jumlahmenang":6,"lelangmenang":"3762042, 5821042, 5843042, 7092042, 7237042, 7627042","menangperpenawaran":0.333333,"group":5},{"id":143,"name":"PT TIRTA BUMI KENCANA","jumlahmenang":5,"lelangmenang":"3769042, 4486042, 5814042, 5817042, 7091042","menangperpenawaran":0.416667,"group":4},{"id":144,"name":"PT. NISAJANA HASNA RIZQY","jumlahmenang":7,"lelangmenang":"3772042, 3783042, 4474042, 5794042, 5809042, 7068042, 7069042","menangperpenawaran":0.7,"group":4},{"id":145,"name":"TRADHA","jumlahmenang":9,"lelangmenang":"4280042, 5877042, 7073042, 7080042, 7618042, 7635042, 7636042, 7637042, 7655042","menangperpenawaran":0.692308,"group":5},{"id":146,"name":"INTI BANGUN SARANA","jumlahmenang":7,"lelangmenang":"3821042, 3828042, 3831042, 3834042, 3835042, 5995042, 7905042","menangperpenawaran":0.7,"group":4},{"id":147,"name":"CV. FAHD ARSIETA","jumlahmenang":17,"lelangmenang":"4393042, 4397042, 4398042, 5963042, 5965042, 5990042, 6173042, 6174042, 6213042, 7127042, 7250042, 7779042, 7890042, 7893042, 7903042, 7941042, 7953042","menangperpenawaran":0.459459,"group":4},{"id":148,"name":"CV. INDOTAMA SUKSES MANDIRI","jumlahmenang":10,"lelangmenang":"3839042, 4322042, 4324042, 5915042, 5916042, 5917042, 5925042, 7820042, 7833042, 8013042","menangperpenawaran":0.588235,"group":4},{"id":149,"name":"CV. ADRIAN MARGA","jumlahmenang":5,"lelangmenang":"3846042, 3934042, 3938042, 3939042, 3940042","menangperpenawaran":0.833333,"group":4},{"id":150,"name":"CV. KRISNA","jumlahmenang":5,"lelangmenang":"3852042, 3858042, 6027042, 6028042, 6030042","menangperpenawaran":0.833333,"group":4},{"id":151,"name":"CV.KARYA RAGIL PUTRA","jumlahmenang":5,"lelangmenang":"3853042, 3854042, 3857042, 3860042, 6032042","menangperpenawaran":0.454545,"group":4},{"id":152,"name":"CV.RAMBU ARTA","jumlahmenang":10,"lelangmenang":"3885042, 3887042, 4222042, 4234042, 4355042, 5928042, 5931042, 5935042, 5937042, 5938042","menangperpenawaran":0.384615,"group":4},{"id":153,"name":"CV. TRUKO RAHAYU","jumlahmenang":8,"lelangmenang":"3859042, 4240042, 4242042, 4246042, 6035042, 6042042, 6043042, 8275042","menangperpenawaran":0.727273,"group":4},{"id":154,"name":"CV. Duta Utama","jumlahmenang":7,"lelangmenang":"3874042, 4326042, 4334042, 4341042, 6223042, 7826042, 7827042","menangperpenawaran":0.5,"group":4},{"id":155,"name":"CV. KRESNA MUKTI ABADI","jumlahmenang":5,"lelangmenang":"3868042, 3870042, 6033042, 6034042, 6188042","menangperpenawaran":0.625,"group":4},{"id":156,"name":"CV. BAROKAH ABADI","jumlahmenang":8,"lelangmenang":"4349042, 4350042, 4351042, 4352042, 4353042, 4354042, 5932042, 5933042","menangperpenawaran":0.571429,"group":4},{"id":157,"name":"KURNIA PATRIA","jumlahmenang":5,"lelangmenang":"4056042, 4058042, 4060042, 4062042, 4245042","menangperpenawaran":0.357143,"group":4},{"id":158,"name":"CV. MANDIRI ABADI","jumlahmenang":9,"lelangmenang":"3930042, 3931042, 3951042, 3962042, 4356042, 4357042, 5909042, 5910042, 5912042","menangperpenawaran":0.5625,"group":4},{"id":159,"name":"mitra jasa cv","jumlahmenang":8,"lelangmenang":"3950042, 3954042, 3956042, 4229042, 5970042, 5972042, 5996042, 6001042","menangperpenawaran":0.285714,"group":4},{"id":160,"name":"CV. DULCHOMINDO","jumlahmenang":6,"lelangmenang":"3974042, 5969042, 5973042, 5985042, 5998042, 6002042","menangperpenawaran":0.26087,"group":4},{"id":161,"name":"CV. TRI AGUNG KARYA","jumlahmenang":6,"lelangmenang":"3977042, 4425042, 7128042, 7131042, 7132042, 7901042","menangperpenawaran":0.857143,"group":4},{"id":162,"name":"CV. CIPTA KARYA","jumlahmenang":10,"lelangmenang":"4424042, 5885042, 5886042, 5888042, 5889042, 5890042, 7942042, 7960042, 8021042, 8100042","menangperpenawaran":0.555556,"group":4},{"id":163,"name":"cv. satrio","jumlahmenang":5,"lelangmenang":"3980042, 3982042, 3983042, 4396042, 7758042","menangperpenawaran":0.5,"group":4},{"id":164,"name":"CV. Indo Tama","jumlahmenang":14,"lelangmenang":"3981042, 3984042, 3985042, 3986042, 3987042, 5882042, 5883042, 5884042, 5891042, 5892042, 5893042, 7954042, 7956042, 7958042","menangperpenawaran":0.538462,"group":4},{"id":165,"name":"CV. PERDANA JAYA","jumlahmenang":11,"lelangmenang":"4010042, 4011042, 5954042, 5955042, 5956042, 5957042, 5958042, 5959042, 6076042, 6300042, 6301042","menangperpenawaran":0.733333,"group":4},{"id":166,"name":"CV. SARANA JASA","jumlahmenang":5,"lelangmenang":"4007042, 4310042, 6234042, 6235042, 6239042","menangperpenawaran":0.555556,"group":4},{"id":167,"name":"CEMARA SEWU","jumlahmenang":8,"lelangmenang":"4028042, 4036042, 4383042, 5050042, 6093042, 6094042, 6096042, 6097042","menangperpenawaran":1,"group":4},{"id":168,"name":"cv. ardan","jumlahmenang":7,"lelangmenang":"4034042, 4035042, 4309042, 4372042, 4373042, 4374042, 4635042","menangperpenawaran":0.875,"group":4},{"id":169,"name":"CANDRA DEWI","jumlahmenang":7,"lelangmenang":"4061042, 4241042, 6006042, 6038042, 6045042, 6316042, 7749042","menangperpenawaran":0.5,"group":4},{"id":170,"name":"CV. GIRI JATI","jumlahmenang":9,"lelangmenang":"4063042, 4420042, 6037042, 6193042, 6201042, 6202042, 7746042, 7747042, 7778042","menangperpenawaran":0.529412,"group":4},{"id":171,"name":"CV. PUTRA UTAMA","jumlahmenang":7,"lelangmenang":"4219042, 4244042, 6048042, 6195042, 6318042, 7745042, 7751042","menangperpenawaran":0.583333,"group":4},{"id":172,"name":"CV. PURNAMA ABADI","jumlahmenang":6,"lelangmenang":"4127042, 4443042, 4446042, 4447042, 4448042, 4450042","menangperpenawaran":0.75,"group":5},{"id":173,"name":"CV JAYA SEMPURNA ABADI","jumlahmenang":5,"lelangmenang":"4216042, 6015042, 6024042, 8258042, 9950042","menangperpenawaran":0.714286,"group":5},{"id":174,"name":"CV. SETYA MITRA","jumlahmenang":8,"lelangmenang":"4248042, 6196042, 6197042, 6198042, 6200042, 7788042, 7791042, 7792042","menangperpenawaran":0.666667,"group":4},{"id":175,"name":"CV. MANUNGGAL SAKTI","jumlahmenang":6,"lelangmenang":"4399042, 4631042, 4632042, 4633042, 4636042, 6077042","menangperpenawaran":0.3,"group":4},{"id":176,"name":"CV.HEKSA MANDIRI","jumlahmenang":5,"lelangmenang":"4585042, 4638042, 6080042, 6081042, 6299042","menangperpenawaran":1,"group":5},{"id":177,"name":"rekan rukun berkarya","jumlahmenang":7,"lelangmenang":"4798042, 5960042, 5961042, 5966042, 5967042, 5982042, 7120042","menangperpenawaran":0.875,"group":4},{"id":178,"name":"CV.Mahottama","jumlahmenang":5,"lelangmenang":"5418042, 6308042, 6766042, 7231042, 9148042","menangperpenawaran":0.5,"group":4},{"id":179,"name":"CV. TEJAKUSUMA PUTRA","jumlahmenang":5,"lelangmenang":"5894042, 5895042, 5897042, 5962042, 5974042","menangperpenawaran":0.833333,"group":4},{"id":180,"name":"PT. ADHIYASA DESICON","jumlahmenang":6,"lelangmenang":"6304042, 6726042, 8134042, 8226042, 9833042, 9834042","menangperpenawaran":0.857143,"group":4},{"id":181,"name":"CV.CITRA LESTARI","jumlahmenang":6,"lelangmenang":"6764042, 8135042, 8136042, 8137042, 8142042, 8143042","menangperpenawaran":0.375,"group":4},{"id":182,"name":"CV. GIRI JATI","jumlahmenang":5,"lelangmenang":"530042, 533042, 2012042, 2043042, 2195042","menangperpenawaran":0.833333,"group":4},{"id":183,"name":"CV. MERTOYUDAN JAYA","jumlahmenang":5,"lelangmenang":"472042, 504042, 1986042, 1998042, 2231042","menangperpenawaran":1,"group":4},{"id":184,"name":"CV. SARANA JASA","jumlahmenang":5,"lelangmenang":"549042, 1925042, 1927042, 1946042, 1947042","menangperpenawaran":0.5,"group":4},{"id":185,"name":"CV. INDOTAMA SUKSES MANDIRI","jumlahmenang":5,"lelangmenang":"565042, 566042, 2126042, 2127042, 2130042","menangperpenawaran":0.625,"group":4},{"id":186,"name":"CV.SUMBER BIBIT SUBUR","jumlahmenang":5,"lelangmenang":"2499042, 2502042, 7383042, 7431042, 8368042","menangperpenawaran":0.416667,"group":4},{"id":187,"name":"CV. BAROKAH","jumlahmenang":5,"lelangmenang":"6373042, 6378042, 6431042, 6433042, 8728042","menangperpenawaran":0.625,"group":4},{"id":188,"name":"CV. Damar Kumala","jumlahmenang":5,"lelangmenang":"2149042, 2378042, 4182042, 4186042, 4205042","menangperpenawaran":0.5,"group":4},{"id":189,"name":"CV.TRI HITA KARANA","jumlahmenang":7,"lelangmenang":"2280042, 2375042, 2611042, 2644042, 4549042, 4699042, 6739042","menangperpenawaran":0.538462,"group":4},{"id":190,"name":"PT. Trikarsa Buwana Persada Gemilang","jumlahmenang":5,"lelangmenang":"2283042, 4515042, 4856042, 6324042, 6413042","menangperpenawaran":0.5,"group":4},{"id":191,"name":"CV. DUTA","jumlahmenang":5,"lelangmenang":"2321042, 4470042, 6323042, 8352042, 9109042","menangperpenawaran":0.555556,"group":4},{"id":192,"name":"PT. TUMBUH JAYA DESAIN","jumlahmenang":7,"lelangmenang":"4177042, 4648042, 6414042, 6440042, 8403042, 8548042, 8549042","menangperpenawaran":0.7,"group":4},{"id":193,"name":"PT. PERMANA CITRA","jumlahmenang":6,"lelangmenang":"4181042, 4202042, 4932042, 5716042, 6490042, 9367042","menangperpenawaran":0.75,"group":4},{"id":194,"name":"CV. ARTHA GEMILANG ENGINEERING","jumlahmenang":5,"lelangmenang":"4516042, 4652042, 6738042, 8379042, 8432042","menangperpenawaran":0.5,"group":4},{"id":195,"name":"CV. PIRAMIDA KREASI MANDIRI","jumlahmenang":5,"lelangmenang":"4646042, 6441042, 6699042, 8520042, 8530042","menangperpenawaran":0.714286,"group":4},{"id":196,"name":"CV. NAMORA","jumlahmenang":8,"lelangmenang":"784042, 1192042, 1211042, 2407042, 2539042, 2544042, 2678042, 2744042","menangperpenawaran":0.727273,"group":4},{"id":197,"name":"PT. SAKAPILAR","jumlahmenang":7,"lelangmenang":"1170042, 1173042, 1649042, 2541042, 3009042, 3102042, 4413042","menangperpenawaran":0.583333,"group":4},{"id":198,"name":"PT. Bhakti Cahayasih","jumlahmenang":9,"lelangmenang":"2405042, 4434042, 7320042, 9475042, 9608042, 9690042, 10694042, 11052042, 11215042","menangperpenawaran":0.473684,"group":4},{"id":199,"name":"PT. DWI MUSTIKA","jumlahmenang":6,"lelangmenang":"2349042, 4414042, 6407042, 7526042, 9375042, 10680042","menangperpenawaran":0.545455,"group":4},{"id":200,"name":"PT. CITRA INSAN KUSUMA","jumlahmenang":12,"lelangmenang":"2787042, 3105042, 3630042, 4722042, 4796042, 5275042, 5662042, 6487042, 6754042, 7313042, 8929042, 9770042","menangperpenawaran":0.6,"group":4},{"id":201,"name":"PT. KARSA INSAN PERSADA","jumlahmenang":9,"lelangmenang":"3007042, 4320042, 4605042, 4608042, 4998042, 5710042, 5757042, 6574042, 7222042","menangperpenawaran":0.529412,"group":4},{"id":202,"name":"cv. BISMA KARYA MEDIKA","jumlahmenang":6,"lelangmenang":"5756042, 5764042, 5769042, 5777042, 7336042, 9435042","menangperpenawaran":0.375,"group":4},{"id":203,"name":"CV. JAVA DESIGN CONSULTANT","jumlahmenang":7,"lelangmenang":"4950042, 5431042, 5527042, 6399042, 6943042, 7056042, 9211042","menangperpenawaran":1,"group":4},{"id":204,"name":"CV. HRV PLANNER CONSULTANT","jumlahmenang":5,"lelangmenang":"5292042, 5425042, 7204042, 9346042, 9598042","menangperpenawaran":0.555556,"group":4},{"id":205,"name":"CV. TRI KARYA","jumlahmenang":7,"lelangmenang":"1219042, 2356042, 3128042, 3130042, 5246042, 5247042, 5249042","menangperpenawaran":0.777778,"group":4},{"id":206,"name":"CV. BAROKAH","jumlahmenang":8,"lelangmenang":"9299042, 9304042, 9629042, 9650042, 9798042, 9800042, 9802042, 9986042","menangperpenawaran":0.571429,"group":5},{"id":207,"name":"CV.Ragil Jaya","jumlahmenang":5,"lelangmenang":"9190042, 9192042, 10088042, 10090042, 10092042","menangperpenawaran":0.416667,"group":4},{"id":208,"name":"CV. DEYAN PUTRA UTAMA","jumlahmenang":5,"lelangmenang":"4435042, 4729042, 5503042, 6103042, 7401042","menangperpenawaran":0.5,"group":4},{"id":209,"name":"CV.SUMBER BIBIT SUBUR","jumlahmenang":5,"lelangmenang":"5036042, 5121042, 5531042, 6350042, 7396042","menangperpenawaran":0.294118,"group":4},{"id":210,"name":"CV.Ragil Jaya","jumlahmenang":11,"lelangmenang":"5037042, 5499042, 5524042, 5685042, 5686042, 5687042, 5735042, 6560042, 6561042, 6783042, 6784042","menangperpenawaran":0.611111,"group":4},{"id":211,"name":"PT Sumber Cakung","jumlahmenang":5,"lelangmenang":"4100014, 4101014, 10635014, 10690014, 2789042","menangperpenawaran":1,"group":4},{"id":212,"name":"CV. IDEA MITRA KOMUNIKA","jumlahmenang":7,"lelangmenang":"6444042, 6718042, 6974042, 8244042, 8290042, 8826042, 9183042","menangperpenawaran":1,"group":4},{"id":213,"name":"PT. PESONA PERMATA BUANA","jumlahmenang":5,"lelangmenang":"6537042, 6963042, 7415042, 8551042, 9705042","menangperpenawaran":0.625,"group":4},{"id":214,"name":"CV RELLIS BARU","jumlahmenang":5,"lelangmenang":"1740013, 2603013, 2671013, 3782013, 3969013","menangperpenawaran":0.555556,"group":4},{"id":215,"name":"PT. ANDALAN MITRA NUSANTARA","jumlahmenang":6,"lelangmenang":"1859013, 2511013, 2805013, 3592013, 3825013, 3889013","menangperpenawaran":0.75,"group":4},{"id":216,"name":"PT.YOSEPH FARMA","jumlahmenang":5,"lelangmenang":"339013, 340013, 1021013, 1912013, 1982013","menangperpenawaran":0.833333,"group":4},{"id":217,"name":"PT. ARMADA HADA GRAHA","jumlahmenang":5,"lelangmenang":"8149042, 8180042, 8216042, 8248042, 8327042","menangperpenawaran":1,"group":4},{"id":218,"name":"CV. BATAS (BANGUN TATA SARANA)","jumlahmenang":6,"lelangmenang":"7732042, 7733042, 7735042, 7736042, 7740042, 7741042","menangperpenawaran":0.75,"group":4},{"id":219,"name":"CV. BAGASKARA","jumlahmenang":6,"lelangmenang":"7804042, 7805042, 7806042, 7807042, 7808042, 7809042","menangperpenawaran":1,"group":4},{"id":220,"name":"rekan rukun berkarya","jumlahmenang":5,"lelangmenang":"7850042, 7851042, 7872042, 7873042, 7874042","menangperpenawaran":0.833333,"group":4},{"id":221,"name":"CV. DULCHOMINDO","jumlahmenang":5,"lelangmenang":"7860042, 7861042, 7864042, 7868042, 7870042","menangperpenawaran":0.714286,"group":4},{"id":222,"name":"PT. HALLO WISATA","jumlahmenang":8,"lelangmenang":"10704042, 10863042, 11037042, 11039042, 11056042, 11166042, 11379042, 11382042","menangperpenawaran":0.571429,"group":4},{"id":223,"name":"PT. PESONA PERMATA BUANA","jumlahmenang":7,"lelangmenang":"10743042, 10782042, 10859042, 11173042, 11254042, 11255042, 11380042","menangperpenawaran":0.538462,"group":4},{"id":224,"name":"PT.MARGA KARYA","jumlahmenang":5,"lelangmenang":"10198042, 10244042, 10256042, 10284042, 10306042","menangperpenawaran":0.625,"group":4},{"id":225,"name":"pt nurcahya jaya mandiri","jumlahmenang":6,"lelangmenang":"10227042, 10230042, 10232042, 10238042, 10305042, 10307042","menangperpenawaran":0.461538,"group":4},{"id":226,"name":"PT. JAYA SEMPURNA SAKTI","jumlahmenang":5,"lelangmenang":"10246042, 10248042, 10250042, 10274042, 10497042","menangperpenawaran":0.2,"group":4},{"id":227,"name":"PT. ARMADA HADA GRAHA","jumlahmenang":9,"lelangmenang":"10239042, 10241042, 10251042, 10259042, 10262042, 10264042, 10266042, 10296042, 10594042","menangperpenawaran":0.818182,"group":4},{"id":228,"name":"CAHAYA ANURA","jumlahmenang":6,"lelangmenang":"10330042, 10331042, 10649042, 10706042, 10707042, 10758042","menangperpenawaran":0.75,"group":4},{"id":229,"name":"CV. BATAS (BANGUN TATA SARANA)","jumlahmenang":7,"lelangmenang":"10349042, 10367042, 10369042, 10370042, 10470042, 10484042, 10622042","menangperpenawaran":0.583333,"group":4},{"id":230,"name":"CV.SERAYU SAKTI","jumlahmenang":5,"lelangmenang":"10371042, 10408042, 10423042, 10485042, 10731042","menangperpenawaran":1,"group":4},{"id":231,"name":"CV. GIRI JATI","jumlahmenang":6,"lelangmenang":"10625042, 10670042, 10671042, 10678042, 10730042, 10930042","menangperpenawaran":0.857143,"group":4},{"id":232,"name":"PT. AGRASINAR PURIPRATAMA","jumlahmenang":6,"lelangmenang":"10656042, 10659042, 10661042, 10662042, 11011042, 11247042","menangperpenawaran":1,"group":4},{"id":233,"name":"CV. Hasta Mandiri","jumlahmenang":6,"lelangmenang":"10696042, 10943042, 10944042, 10945042, 10946042, 10947042","menangperpenawaran":1,"group":4},{"id":234,"name":"CV. Madani Callysta Saibuyun","jumlahmenang":5,"lelangmenang":"10801042, 10951042, 10953042, 11014042, 11071042","menangperpenawaran":0.833333,"group":4},{"id":235,"name":"CV. JAVA DESIGN CONSULTANT","jumlahmenang":5,"lelangmenang":"10972042, 11026042, 11115042, 11118042, 11278042","menangperpenawaran":0.714286,"group":4},{"id":236,"name":"PT. EMILIA JAYA ABADI","jumlahmenang":6,"lelangmenang":"11125042, 11131042, 11146042, 11165042, 11185042, 11197042","menangperpenawaran":1,"group":4},{"id":237,"name":"CV. SOLUSI ARYA PRIMA","jumlahmenang":6,"lelangmenang":"1743042, 2277042, 3289042, 4546042, 5657042, 7476042","menangperpenawaran":0.352941,"group":4},{"id":238,"name":"PT PURA BARUTAMA","jumlahmenang":5,"lelangmenang":"2532042, 3536042, 4098042, 4133042, 8002042","menangperpenawaran":0.714286,"group":4},{"id":239,"name":"CV.GELARAN JAYA MANUNGGAL","jumlahmenang":8,"lelangmenang":"1369042, 2996042, 2997042, 3000042, 3022042, 3028042, 3045042, 3046042","menangperpenawaran":0.571429,"group":4},{"id":240,"name":"CV. HRV PLANNER CONSULTANT","jumlahmenang":6,"lelangmenang":"5069042, 6519042, 6622042, 8213042, 8736042, 9918042","menangperpenawaran":1,"group":4},{"id":241,"name":"PT. ANEKA GAS INDUSTRI","jumlahmenang":6,"lelangmenang":"3846014, 9360014, 16948014, 22244014, 24619014, 25698014","menangperpenawaran":1,"group":4},{"id":242,"name":"CV. Mulya Jaya","jumlahmenang":5,"lelangmenang":"3837014, 10957014, 18097014, 22212014, 28930014","menangperpenawaran":0.833333,"group":5},{"id":243,"name":"PT.RAJAWALI NUSINDO","jumlahmenang":5,"lelangmenang":"6153014, 6262014, 9423014, 17256014, 23753014","menangperpenawaran":0.625,"group":5},{"id":244,"name":"CV. Kridaya","jumlahmenang":6,"lelangmenang":"8463014, 9196014, 9311014, 10061014, 15403014, 16533014","menangperpenawaran":0.545455,"group":4},{"id":245,"name":"PT. Jasa Medivest","jumlahmenang":5,"lelangmenang":"10640014, 17200014, 22276014, 25677014, 28992014","menangperpenawaran":1,"group":4},{"id":246,"name":"PT. MITRA ABADI KARYA","jumlahmenang":5,"lelangmenang":"22270014, 22272014, 22279014, 22288014, 28970014","menangperpenawaran":0.833333,"group":4},{"id":247,"name":"cv. BISMA KARYA MEDIKA","jumlahmenang":6,"lelangmenang":"5756042, 5764042, 5769042, 5777042, 7336042, 9435042","menangperpenawaran":0.375,"group":4},{"id":248,"name":"PT.RAJAWALI NUSINDO","jumlahmenang":10,"lelangmenang":"9428014, 9665014, 17221014, 17223014, 22716014, 23928014, 26711014, 27237014, 28665014, 29470014","menangperpenawaran":0.666667,"group":5},{"id":249,"name":"CV. SAPTA PUTRA MEKAR","jumlahmenang":6,"lelangmenang":"10700014, 10773014, 19215014, 19246014, 21762014, 25424014","menangperpenawaran":0.75,"group":4},{"id":250,"name":"PT.YOSEPH FARMA","jumlahmenang":5,"lelangmenang":"339013, 340013, 1021013, 1912013, 1982013","menangperpenawaran":0.833333,"group":4}],"links":[{"source":1,"target":0,"value":1},{"source":2,"target":0,"value":1},{"source":3,"target":0,"value":1},{"source":4,"target":0,"value":1},{"source":5,"target":0,"value":1},{"source":6,"target":0,"value":1},{"source":7,"target":1,"value":1},{"source":8,"target":1,"value":1},{"source":9,"target":1,"value":1},{"source":10,"target":1,"value":1},{"source":11,"target":1,"value":1},{"source":12,"target":1,"value":1},{"source":13,"target":1,"value":1},{"source":14,"target":1,"value":1},{"source":15,"target":1,"value":1},{"source":16,"target":1,"value":1},{"source":17,"target":1,"value":1},{"source":18,"target":1,"value":1},{"source":19,"target":1,"value":1},{"source":20,"target":1,"value":1},{"source":21,"target":1,"value":1},{"source":22,"target":1,"value":1},{"source":23,"target":1,"value":1},{"source":24,"target":1,"value":1},{"source":25,"target":1,"value":1},{"source":26,"target":1,"value":1},{"source":27,"target":1,"value":1},{"source":28,"target":1,"value":1},{"source":29,"target":1,"value":1},{"source":30,"target":1,"value":1},{"source":31,"target":1,"value":1},{"source":32,"target":1,"value":1},{"source":33,"target":1,"value":1},{"source":34,"target":1,"value":1},{"source":35,"target":1,"value":1},{"source":36,"target":1,"value":1},{"source":37,"target":1,"value":1},{"source":38,"target":1,"value":1},{"source":39,"target":1,"value":1},{"source":40,"target":1,"value":1},{"source":41,"target":1,"value":1},{"source":42,"target":1,"value":1},{"source":43,"target":1,"value":1},{"source":44,"target":1,"value":1},{"source":45,"target":1,"value":1},{"source":46,"target":1,"value":1},{"source":47,"target":1,"value":1},{"source":48,"target":2,"value":1},{"source":49,"target":3,"value":1},{"source":50,"target":4,"value":1},{"source":51,"target":5,"value":1},{"source":52,"target":5,"value":1},{"source":53,"target":5,"value":1},{"source":54,"target":5,"value":1},{"source":55,"target":6,"value":1},{"source":56,"target":7,"value":1},{"source":57,"target":7,"value":1},{"source":58,"target":8,"value":1},{"source":59,"target":8,"value":1},{"source":60,"target":8,"value":1},{"source":61,"target":9,"value":1},{"source":62,"target":10,"value":1},{"source":63,"target":10,"value":1},{"source":64,"target":10,"value":1},{"source":65,"target":10,"value":1},{"source":66,"target":10,"value":1},{"source":67,"target":10,"value":1},{"source":68,"target":10,"value":1},{"source":69,"target":11,"value":1},{"source":70,"target":11,"value":1},{"source":71,"target":11,"value":1},{"source":72,"target":11,"value":1},{"source":73,"target":11,"value":1},{"source":74,"target":11,"value":1},{"source":75,"target":12,"value":1},{"source":76,"target":13,"value":1},{"source":77,"target":14,"value":1},{"source":78,"target":14,"value":1},{"source":79,"target":15,"value":1},{"source":80,"target":15,"value":1},{"source":81,"target":15,"value":1},{"source":82,"target":15,"value":1},{"source":83,"target":15,"value":1},{"source":84,"target":15,"value":1},{"source":85,"target":15,"value":1},{"source":86,"target":15,"value":1},{"source":87,"target":15,"value":1},{"source":88,"target":15,"value":1},{"source":89,"target":16,"value":1},{"source":90,"target":16,"value":1},{"source":91,"target":16,"value":1},{"source":92,"target":16,"value":1},{"source":93,"target":16,"value":1},{"source":94,"target":16,"value":1},{"source":95,"target":16,"value":1},{"source":96,"target":16,"value":1},{"source":97,"target":16,"value":1},{"source":98,"target":17,"value":1},{"source":99,"target":18,"value":1},{"source":100,"target":19,"value":1},{"source":101,"target":20,"value":1},{"source":102,"target":20,"value":1},{"source":103,"target":20,"value":1},{"source":104,"target":20,"value":1},{"source":105,"target":20,"value":1},{"source":106,"target":20,"value":1},{"source":107,"target":20,"value":1},{"source":108,"target":21,"value":1},{"source":109,"target":21,"value":1},{"source":110,"target":22,"value":1},{"source":111,"target":22,"value":1},{"source":112,"target":23,"value":1},{"source":113,"target":24,"value":1},{"source":114,"target":24,"value":1},{"source":115,"target":24,"value":1},{"source":116,"target":24,"value":1},{"source":117,"target":24,"value":1},{"source":118,"target":24,"value":1},{"source":119,"target":24,"value":1},{"source":120,"target":24,"value":1},{"source":121,"target":24,"value":1},{"source":122,"target":24,"value":1},{"source":123,"target":24,"value":1},{"source":124,"target":24,"value":1},{"source":125,"target":24,"value":1},{"source":126,"target":24,"value":1},{"source":127,"target":24,"value":1},{"source":128,"target":24,"value":1},{"source":129,"target":24,"value":1},{"source":130,"target":24,"value":1},{"source":131,"target":24,"value":1},{"source":132,"target":24,"value":1},{"source":133,"target":24,"value":1},{"source":134,"target":24,"value":1},{"source":135,"target":24,"value":1},{"source":136,"target":24,"value":1},{"source":137,"target":24,"value":1},{"source":138,"target":24,"value":1},{"source":139,"target":24,"value":1},{"source":140,"target":24,"value":1},{"source":141,"target":24,"value":1},{"source":142,"target":24,"value":1},{"source":143,"target":24,"value":1},{"source":144,"target":24,"value":1},{"source":145,"target":24,"value":1},{"source":146,"target":24,"value":1},{"source":147,"target":24,"value":1},{"source":148,"target":24,"value":1},{"source":149,"target":24,"value":1},{"source":150,"target":24,"value":1},{"source":151,"target":24,"value":1},{"source":152,"target":24,"value":1},{"source":153,"target":24,"value":1},{"source":154,"target":24,"value":1},{"source":155,"target":24,"value":1},{"source":156,"target":24,"value":1},{"source":157,"target":24,"value":1},{"source":158,"target":24,"value":1},{"source":159,"target":24,"value":1},{"source":160,"target":24,"value":1},{"source":161,"target":24,"value":1},{"source":162,"target":24,"value":1},{"source":163,"target":24,"value":1},{"source":164,"target":24,"value":1},{"source":165,"target":24,"value":1},{"source":166,"target":24,"value":1},{"source":167,"target":24,"value":1},{"source":168,"target":24,"value":1},{"source":169,"target":24,"value":1},{"source":170,"target":24,"value":1},{"source":171,"target":24,"value":1},{"source":172,"target":24,"value":1},{"source":173,"target":24,"value":1},{"source":174,"target":24,"value":1},{"source":175,"target":24,"value":1},{"source":176,"target":24,"value":1},{"source":177,"target":24,"value":1},{"source":178,"target":24,"value":1},{"source":179,"target":24,"value":1},{"source":180,"target":24,"value":1},{"source":181,"target":24,"value":1},{"source":182,"target":25,"value":1},{"source":183,"target":26,"value":1},{"source":184,"target":27,"value":1},{"source":185,"target":28,"value":1},{"source":186,"target":29,"value":1},{"source":187,"target":29,"value":1},{"source":188,"target":30,"value":1},{"source":189,"target":30,"value":1},{"source":190,"target":30,"value":1},{"source":191,"target":30,"value":1},{"source":192,"target":30,"value":1},{"source":193,"target":30,"value":1},{"source":194,"target":30,"value":1},{"source":195,"target":30,"value":1},{"source":196,"target":31,"value":1},{"source":197,"target":31,"value":1},{"source":198,"target":31,"value":1},{"source":199,"target":31,"value":1},{"source":200,"target":31,"value":1},{"source":201,"target":31,"value":1},{"source":202,"target":32,"value":1},{"source":203,"target":33,"value":1},{"source":204,"target":33,"value":1},{"source":205,"target":34,"value":1},{"source":206,"target":35,"value":1},{"source":207,"target":35,"value":1},{"source":208,"target":36,"value":1},{"source":209,"target":36,"value":1},{"source":210,"target":36,"value":1},{"source":211,"target":37,"value":1},{"source":212,"target":38,"value":1},{"source":213,"target":38,"value":1},{"source":214,"target":39,"value":1},{"source":215,"target":39,"value":1},{"source":216,"target":40,"value":1},{"source":217,"target":41,"value":1},{"source":218,"target":42,"value":1},{"source":219,"target":43,"value":1},{"source":220,"target":44,"value":1},{"source":221,"target":44,"value":1},{"source":222,"target":45,"value":1},{"source":223,"target":45,"value":1},{"source":224,"target":46,"value":1},{"source":225,"target":46,"value":1},{"source":226,"target":46,"value":1},{"source":227,"target":46,"value":1},{"source":228,"target":46,"value":1},{"source":229,"target":46,"value":1},{"source":230,"target":46,"value":1},{"source":231,"target":46,"value":1},{"source":232,"target":46,"value":1},{"source":233,"target":46,"value":1},{"source":234,"target":47,"value":1},{"source":235,"target":47,"value":1},{"source":236,"target":47,"value":1},{"source":237,"target":48,"value":1},{"source":238,"target":48,"value":1},{"source":239,"target":49,"value":1},{"source":240,"target":50,"value":1},{"source":241,"target":51,"value":1},{"source":242,"target":52,"value":1},{"source":243,"target":52,"value":1},{"source":244,"target":52,"value":1},{"source":245,"target":52,"value":1},{"source":246,"target":52,"value":1},{"source":247,"target":53,"value":1},{"source":248,"target":54,"value":1},{"source":249,"target":54,"value":1},{"source":250,"target":55,"value":1}]}